{
  "author": "Pete Cooke", 
  "behaviour": {
    "cameras": true, 
    "destroysfloor": true, 
    "timebombspeed": 0
  }, 
  "conditions": {
    "klondikes": 1, 
    "robots": 1, 
    "timelimit": 0
  }, 
  "elements": {
    "0": {
      "0": [{"f": "---", "o": "---"}, {"f": "---", "o": "---"}, {"f": "---", "o": "---"}, {"f": "FLR", "o": "HOP"}, {"f": "---", "o": "---"}, {"f": "---", "o": "---"}], 
      "1": [{"f": "---", "o": "---"}, {"f": "FLR", "o": "---"}, {"f": "---", "o": "---"}, {"f": "FLR", "o": "REL"}, {"f": "FLR", "o": "---"}, {"f": "---", "o": "---"}], 
      "2": [{"f": "---", "o": "---"}, {"f": "LFD", "o": "---"}, {"f": "---", "o": "---"}, {"f": "LFD", "o": "---"}, {"f": "---", "o": "---"}, {"f": "---", "o": "---"}], 
      "3": [{"f": "BOX", "o": "---"}, {"f": "LFU", "o": "---"}, {"f": "BOX", "o": "---"}, {"f": "LFU", "o": "---"}, {"f": "BOX", "o": "---"}, {"f": "---", "o": "---"}], 
      "4": [{"f": "---", "o": "---"}, {"f": "FLR", "o": "ZAP"}, {"f": "---", "o": "---"}, {"f": "FLR", "o": "PSH"}, {"f": "---", "o": "---"}, {"f": "---", "o": "---"}]
    }, 
    "1": {
      "0": [{"f": "---", "o": "---"}, {"f": "---", "o": "---"}, {"f": "---", "o": "---"}, {"f": "---", "o": "---"}, {"f": "---", "o": "---"}, {"f": "---", "o": "---"}], 
      "1": [{"f": "---", "o": "---"}, {"f": "---", "o": "---"}, {"f": "---", "o": "---"}, {"f": "---", "o": "---"}, {"f": "---", "o": "---"}, {"f": "---", "o": "---"}], 
      "2": [{"f": "FLR", "o": "KLD"}, {"f": "---", "o": "---"}, {"f": "---", "o": "---"}, {"f": "---", "o": "---"}, {"f": "---", "o": "---"}, {"f": "---", "o": "---"}], 
      "3": [{"f": "FLR", "o": "---"}, {"f": "---", "o": "---"}, {"f": "FLR", "o": "---"}, {"f": "---", "o": "---"}, {"f": "FLR", "o": "---"}, {"f": "FLR", "o": "---"}], 
      "4": [{"f": "---", "o": "---"}, {"f": "---", "o": "---"}, {"f": "---", "o": "---"}, {"f": "---", "o": "---"}, {"f": "---", "o": "---"}, {"f": "FLR", "o": "GRB"}]
    }
  }, 
  "fx": {
    "groundcolor1": "0xFF787896", 
    "groundcolor2": "0xFF9696B4", 
    "groundheight": 3, 
    "liftcolor": "0xFFFFFFFF", 
    "moons": 3, 
    "pattern": 3, 
    "patterncolor1": "0xFF5A96D2", 
    "patterncolor2": "0xFF5A5AD2", 
    "skycolor1": "0xFF787896", 
    "skycolor2": "0xFF00001E", 
    "stars": 100, 
    "style": 0, 
    "suncolor": "0xFFFFFFFF", 
    "sunsize": 2
  }, 
  "id": "007", 
  "title": "Up and Down and Up and Down", 
  "version": 1
}